tests/__init__.py
tests/blub.py
tests/iir_prefilter.py
tests/test_compare_reference.py
tests/test_fbank.py
tests/test_torch.py
torch_pesq/__init__.py
torch_pesq/bark.py
torch_pesq/loss.py
torch_pesq/loudness.py
torch_pesq-0.1.2.dist-info/LICENSE
torch_pesq-0.1.2.dist-info/METADATA
torch_pesq-0.1.2.dist-info/WHEEL
torch_pesq-0.1.2.dist-info/top_level.txt
torch_pesq-0.1.2.dist-info/RECORD
