Metadata-Version: 2.1
Name: torch-pesq
Version: 0.1.2
Summary: PyTorch implementation of the Perceptual Evaluation of Speech Quality
Home-page: https://github.com/audiolabs/torch-pesq
Author: Lorenz Schmidt
Author-email: lorenz.schmidt@audiolabs-erlangen.de
License: MIT
Classifier: Development Status :: 4 - Beta
Classifier: Intended Audience :: Science/Research
Classifier: License :: OSI Approved :: MIT License
Classifier: Programming Language :: Python :: 3
License-File: LICENSE
Requires-Dist: numpy
Requires-Dist: torch
Requires-Dist: scipy
Requires-Dist: torchaudio
Requires-Dist: torchtyping
Requires-Dist: typeguard
Provides-Extra: all
Requires-Dist: torch-pesq[tests] ; extra == 'all'
Requires-Dist: torch-pesq[docs] ; extra == 'all'
Provides-Extra: docs
Requires-Dist: sphinx ; extra == 'docs'
Requires-Dist: sphinx-rtd-theme ; extra == 'docs'
Requires-Dist: myst-parser ; extra == 'docs'
Provides-Extra: tests
Requires-Dist: pytest ; extra == 'tests'
Requires-Dist: pytest-black ; extra == 'tests'
Requires-Dist: wheel ; extra == 'tests'
Requires-Dist: pesq ; extra == 'tests'
Requires-Dist: joblib ; extra == 'tests'
